taurex_ace.libs/libgfortran-ed201abd.so.3.0.0
taurex_ace/__init__.py
taurex_ace/chemistry/acechemistry.py
taurex_ace/chemistry/__init__.py
taurex_ace/external/ace.cpython-36m-x86_64-linux-gnu.so
taurex_ace/external/__init__.py
taurex_ace/external/Data/NASA.therm
taurex_ace/external/Data/composes.dat
taurex_ace-1.0.2.dev0.dist-info/top_level.txt
taurex_ace-1.0.2.dev0.dist-info/LICENSE
taurex_ace-1.0.2.dev0.dist-info/entry_points.txt
taurex_ace-1.0.2.dev0.dist-info/RECORD
taurex_ace-1.0.2.dev0.dist-info/WHEEL
taurex_ace-1.0.2.dev0.dist-info/METADATA
