Metadata-Version: 2.1
Name: taurex-ace
Version: 1.0.2.dev0
Summary: ACE equilibrium chemical scheme wrapper built on TauREx
Home-page: UNKNOWN
Author: Ahmed Faris Al-Refaie
Author-email: ahmed.al-refaie.12@ucl.ac.uk
License: BSD
Keywords: exoplanet,chemistrytaurex,plugin,taurex3,atmosphere,atmospheric
Platform: UNKNOWN
Provides: taurex_ace
Requires-Dist: numpy
Requires-Dist: taurex
